jinjapy/__init__.py
jinjapy/pygments.py
jinjapy-0.2.0.dist-info/WHEEL
jinjapy-0.2.0.dist-info/entry_points.txt
jinjapy-0.2.0.dist-info/METADATA
jinjapy-0.2.0.dist-info/RECORD
