Metadata-Version: 2.4
Name: jinjapy
Version: 0.2.0
Summary: New hybrid file format combining a Jinja template with Python code in a frontmatter
Author: Maxime Bouroumeau-Fuseau
Author-email: Maxime Bouroumeau-Fuseau <maxime.bouroumeau@gmail.com>
License-Expression: MIT
Requires-Dist: jinja2>=3.0.0,<4.0.0
Requires-Python: >=3.10
Project-URL: Repository, https://github.com/hyperflask/jinjapy
